MANIFEST.in
README.md
README.rst
setup.py
src/ifs_etc/__init__.py
src/ifs_etc.egg-info/PKG-INFO
src/ifs_etc.egg-info/SOURCES.txt
src/ifs_etc.egg-info/dependency_links.txt
src/ifs_etc.egg-info/requires.txt
src/ifs_etc.egg-info/top_level.txt
src/ifs_etc/common/__init__.py
src/ifs_etc/common/tools.py
src/ifs_etc/etc1d/__init__.py
src/ifs_etc/etc1d/config.py
src/ifs_etc/etc1d/perform_calculation.py
src/ifs_etc/etc1d/source.py
src/ifs_etc/etc2d/__init__.py
src/ifs_etc/etc2d/config.py
src/ifs_etc/etc2d/ifs_etc.py
src/ifs_etc/etc2d/perform_calculation.py
src/ifs_etc/etc2d/snpp.py
src/ifs_etc/etc2d/source.py
src/ifs_etc/refdata/csst/background/earthshine_spec.csv
src/ifs_etc/refdata/csst/background/skybg_50_10.dat
src/ifs_etc/refdata/csst/background/zodi_spec.csv
src/ifs_etc/refdata/csst/ifs/IFU_throughput.dat
src/ifs_etc/refdata/csst/ifs/bigmuse_throughput.txt
src/ifs_etc/refdata/csst/ifs/bigmuse_throughput_test.txt
src/ifs_etc/refdata/csst/ifs/lijiang_CHILI.txt
src/ifs_etc/refdata/csst/ifs/lijiang_guidestar_ccd.txt
src/ifs_etc/refdata/csst/ifs/uv_throughput.txt
src/ifs_etc/refdata/csst/telescope/config.json
src/ifs_etc/refdata/normalization/filters/GALEX_fuv.par
src/ifs_etc/refdata/normalization/filters/GALEX_nuv.par
src/ifs_etc/refdata/normalization/filters/Johnson_B.txt
src/ifs_etc/refdata/normalization/filters/Johnson_I.txt
src/ifs_etc/refdata/normalization/filters/Johnson_R.txt
src/ifs_etc/refdata/normalization/filters/Johnson_U.txt
src/ifs_etc/refdata/normalization/filters/Johnson_V.txt
src/ifs_etc/refdata/normalization/filters/sdss_g.par
src/ifs_etc/refdata/normalization/filters/sdss_i.par
src/ifs_etc/refdata/normalization/filters/sdss_r.par
src/ifs_etc/refdata/normalization/filters/sdss_u.par
src/ifs_etc/refdata/normalization/filters/sdss_z.par
src/ifs_etc/refdata/sed/Readme.txt
src/ifs_etc/refdata/sed/flat_continuum_in_Flambda.dat
src/ifs_etc/refdata/sed/flat_continuum_in_Fnu.dat
src/ifs_etc/refdata/sed/HST_standard_star_spectra/109vir_mod_005.fits
src/ifs_etc/refdata/sed/HST_standard_star_spectra/agk_81d266_stisnic_007.fits
src/ifs_etc/refdata/sed/HST_standard_star_spectra/alpha_lyr_stis_010.fits
