Metadata-Version: 2.1
Name: ifs-etc
Version: 0.1.3
Summary: exposure time calculator
Author: linlin
Author-email: linlin@shao.ac.cn
Requires-Python: >=3
